MANIFEST.in
README.txt
setup.py
XStatic_Angular_Sanitize.egg-info/PKG-INFO
XStatic_Angular_Sanitize.egg-info/SOURCES.txt
XStatic_Angular_Sanitize.egg-info/dependency_links.txt
XStatic_Angular_Sanitize.egg-info/namespace_packages.txt
XStatic_Angular_Sanitize.egg-info/not-zip-safe
XStatic_Angular_Sanitize.egg-info/top_level.txt
xstatic/__init__.py
xstatic/pkg/__init__.py
xstatic/pkg/angular_sanitize/__init__.py
xstatic/pkg/angular_sanitize/data/angular-sanitize.js