Metadata-Version: 1.0
Name: XStatic-Angular-Sanitize
Version: 1.2.1.1
Summary: Angular-Sanitize 1.2.1 (XStatic packaging standard)
Home-page: http://angularjs.org
Author: Maxime Vidori
Author-email: maxime.vidori@enovance.com
License: (same as Angular-Sanitize)
Keywords: angular_sanitize xstatic
Platform: any
